stucco/__init__.py
stucco/detection.py
stucco/movable_sdf.py
stucco/tracking.py
stucco-1.2.1.dist-info/LICENSE.txt
stucco-1.2.1.dist-info/METADATA
stucco-1.2.1.dist-info/WHEEL
stucco-1.2.1.dist-info/top_level.txt
stucco-1.2.1.dist-info/RECORD
