Metadata-Version: 2.1
Name: stucco
Version: 1.2.1
Summary: Soft Tracking Using Contacts for Cluttered Objects
Author-email: Sheng Zhong <zhsh@umich.edu>
Maintainer-email: Sheng Zhong <zhsh@umich.edu>
License: Copyright (c) 2023 University of Michigan ARM Lab
Project-URL: Homepage, https://github.com/UM-ARM-Lab/stucco
Project-URL: Bug Reports, https://github.com/UM-ARM-Lab/stucco/issues
Project-URL: Source, https://github.com/UM-ARM-Lab/stucco
Keywords: robotics,perception,tracking,pytorch,contact
Classifier: Development Status :: 4 - Beta
Classifier: Intended Audience :: Developers
Classifier: License :: OSI Approved :: MIT License
Classifier: Programming Language :: Python :: 3
Classifier: Programming Language :: Python :: 3 :: Only
Requires-Python: >=3.6
License-File: LICENSE.txt
Requires-Dist: torch
Requires-Dist: numpy
Requires-Dist: arm-pytorch-utilities >=0.4
Requires-Dist: pytorch-kinematics
Requires-Dist: pytorch-volumetric
Provides-Extra: test
Requires-Dist: pytest ; extra == 'test'
